promptfunction/__init__.py
promptfunction/prompt_function.py
promptfunction-0.0.1.dist-info/METADATA
promptfunction-0.0.1.dist-info/WHEEL
promptfunction-0.0.1.dist-info/RECORD
